flyingsquid/__init__.py
flyingsquid/_graphs.py
flyingsquid/_lm_parameters.py
flyingsquid/_observables.py
flyingsquid/_triplets.py
flyingsquid/helpers.py
flyingsquid/label_model.py
flyingsquid/pytorch_loss.py
flyingsquid-0.0.0a0.dist-info/LICENSE
flyingsquid-0.0.0a0.dist-info/METADATA
flyingsquid-0.0.0a0.dist-info/WHEEL
flyingsquid-0.0.0a0.dist-info/top_level.txt
flyingsquid-0.0.0a0.dist-info/RECORD
