Metadata-Version: 2.1
Name: flyingsquid
Version: 0.0.0a0
Summary: Weak supervision with triplet methods
Home-page: https://github.com/HazyResearch/flyingsquid
Author: Dan Fu
Author-email: danfu@cs.stanford.edu
License: Apache 2.0
Platform: UNKNOWN
